{
  "fabric:load_conditions": [
    {
      "condition": "fabric:all_mods_loaded",
      "values": [
        "naturalist"
      ]
    }
  ],
  "parent": "minecraft:recipes/root",
  "criteria": {
    "has_duck_egg": {
      "conditions": {
        "items": [
          {
            "items": [
              "naturalist:duck_egg"
            ]
          }
        ]
      },
      "trigger": "minecraft:inventory_changed"
    },
    "has_the_recipe": {
      "conditions": {
        "recipe": "naturalist:duck_egg_crate"
      },
      "trigger": "minecraft:recipe_unlocked"
    }
  },
  "requirements": [
    [
      "has_duck_egg",
      "has_the_recipe"
    ]
  ],
  "rewards": {
    "recipes": [
      "naturalist:duck_egg_crate"
    ]
  },
  "sends_telemetry_event": false
}